main.py
setup.py
Image_Dream.egg-info/PKG-INFO
Image_Dream.egg-info/SOURCES.txt
Image_Dream.egg-info/dependency_links.txt
Image_Dream.egg-info/requires.txt
Image_Dream.egg-info/top_level.txt